AUTHORS.rst
CONTRIBUTING.rst
HISTORY.rst
LICENSE
MANIFEST.in
README.rst
requirements.txt
setup.cfg
setup.py
docs/Makefile
docs/authors.rst
docs/conf.py
docs/contributing.rst
docs/history.rst
docs/index.rst
docs/installation.rst
docs/make.bat
docs/readme.rst
docs/usage.rst
src/flask_gae/__init__.py
src/flask_gae/converters.py
src/flask_gae.egg-info/PKG-INFO
src/flask_gae.egg-info/SOURCES.txt
src/flask_gae.egg-info/dependency_links.txt
src/flask_gae.egg-info/not-zip-safe
src/flask_gae.egg-info/requires.txt
src/flask_gae.egg-info/top_level.txt
tests/__init__.py
tests/test_flask_gae.py