Metadata-Version: 1.1
Name: flask-gae
Version: 0.1.0-20140530
Summary: Commons for Flask running on Google App Engine
Home-page: https://github.com/wooyek/flask-gae
Author: Janusz Skonieczny
Author-email: js@bravelabs.pl
License: BSD
Keywords: flask google app engine
Platform: UNKNOWN
Classifier: Development Status :: 2 - Pre-Alpha
Classifier: Intended Audience :: Developers
Classifier: License :: OSI Approved :: BSD License
Classifier: Natural Language :: English
Classifier: Programming Language :: Python :: 2
Classifier: Programming Language :: Python :: 2.6
Classifier: Programming Language :: Python :: 2.7
Classifier: Programming Language :: Python :: 3
Classifier: Programming Language :: Python :: 3.3
Classifier: Programming Language :: Python :: 3.4
